easyts/__init__.py
easyts/binning.py
easyts/easyts.py
easyts/ldtkld.py
easyts/tsdata.py
easyts/tslpf.py
easyts/util.py
easyts/wlpf.py
EasyTS-0.9.6.dist-info/LICENSE
EasyTS-0.9.6.dist-info/METADATA
EasyTS-0.9.6.dist-info/WHEEL
EasyTS-0.9.6.dist-info/top_level.txt
EasyTS-0.9.6.dist-info/RECORD
